arangoimport/__init__.py
arangoimport/cli.py
arangoimport/connection.py
arangoimport/importer.py
arangoimport/logging.py
arangoimport/utils.py
arangoimport-0.1.11.dist-info/METADATA
arangoimport-0.1.11.dist-info/WHEEL
arangoimport-0.1.11.dist-info/entry_points.txt
arangoimport-0.1.11.dist-info/RECORD
