Metadata-Version: 2.3
Name: arangoimport
Version: 0.1.11
Summary: A high-performance tool for importing Neo4j JSONL graph data exports into ArangoDB
Author: Trent Leslie
Author-email: trent.leslie@phenomehealth.com
Requires-Python: >=3.11
Classifier: Programming Language :: Python :: 3
Classifier: Programming Language :: Python :: 3.11
Classifier: Programming Language :: Python :: 3.12
Classifier: License :: OSI Approved :: MIT License
Classifier: Operating System :: OS Independent
Classifier: Development Status :: 4 - Beta
Classifier: Intended Audience :: Developers
Classifier: Topic :: Database
Requires-Dist: click (>=8.0.0)
Requires-Dist: ijson (>=3.2.3)
Requires-Dist: psutil (>=5.9.0)
Requires-Dist: pyarango (>=2.0.1)
Requires-Dist: python-arango (>=7.5.0)
Requires-Dist: python-dotenv (>=1.0.0)
Requires-Dist: rich (>=10.0.0)
Requires-Dist: tqdm (>=4.65.0)
